inthing/__init__.py
inthing/_version.py
inthing/account.py
inthing/compat.py
inthing/constants.py
inthing/errors.py
inthing/event.py
inthing/events.py
inthing/jsonrpc.py
inthing/rpc.py
inthing/stream.py
inthing/urls.py
inthing/command/__init__.py
inthing/command/app.py
inthing/command/console.py
inthing/command/subcommand.py
inthing/command/sub/__init__.py
inthing/command/sub/capture.py
inthing/command/sub/event.py
inthing/command/sub/screenshot.py
inthing/command/sub/text.py
inthing-0.1.6.dist-info/DESCRIPTION.rst
inthing-0.1.6.dist-info/entry_points.txt
inthing-0.1.6.dist-info/METADATA
inthing-0.1.6.dist-info/metadata.json
inthing-0.1.6.dist-info/pbr.json
inthing-0.1.6.dist-info/RECORD
inthing-0.1.6.dist-info/top_level.txt
inthing-0.1.6.dist-info/WHEEL
inthing-0.1.6.dist-info/zip-safe
