Metadata-Version: 2.0
Name: inthing
Version: 0.1.6
Summary: share realtime streams of events on inthing.io
Home-page: https://inthing.io
Author: Will McGugan
Author-email: will@willmcgugan.com
License: MIT
Platform: any
Classifier: Intended Audience :: Developers
Classifier: License :: OSI Approved :: MIT License
Classifier: Operating System :: OS Independent
Classifier: Programming Language :: Python
Classifier: Programming Language :: Python :: 2.7
Classifier: Programming Language :: Python :: 3.4
Classifier: Programming Language :: Python :: 3.5
Requires-Dist: requests
Requires-Dist: pillow (>=3.1.1)
